scinode_app/__init__.py
scinode_app/app.py
scinode_app/build_node_from_json.py
scinode_app/db.py
scinode_app/init_data.py
scinode_app/utils.py
scinode_app/blueprints/__init__.py
scinode_app/blueprints/component/__init__.py
scinode_app/blueprints/component/component.py
scinode_app/blueprints/component/templates/component_editor.html
scinode_app/blueprints/component/templates/component_exporter.html
scinode_app/blueprints/component/templates/component_importer.html
scinode_app/blueprints/component/templates/component_table.html
scinode_app/blueprints/config/__init__.py
scinode_app/blueprints/config/config.py
scinode_app/blueprints/config/templates/config.html
scinode_app/blueprints/config/templates/daemon_logfile.html
scinode_app/blueprints/node/__init__.py
scinode_app/blueprints/node/node.py
scinode_app/blueprints/node/templates/node_table.html
scinode_app/blueprints/node/templates/node_viewer.html
scinode_app/blueprints/nodetree/__init__.py
scinode_app/blueprints/nodetree/nodetree.py
scinode_app/blueprints/nodetree/utils.py
scinode_app/blueprints/nodetree/templates/nodetree_editor.html
scinode_app/blueprints/nodetree/templates/nodetree_exporter.html
scinode_app/blueprints/nodetree/templates/nodetree_importer.html
scinode_app/blueprints/nodetree/templates/nodetree_table.html
scinode_app/blueprints/nodetree/templates/nodetree_viewer.html
scinode_app/blueprints/template/__init__.py
scinode_app/blueprints/template/template.py
scinode_app/blueprints/template/templates/template_table.html
scinode_app/core/__init__.py
scinode_app/core/node.py
scinode_app/core/nodetree.py
scinode_app/core/rete_adapter.py
scinode_app/static/component_editor.js
scinode_app/static/components.js
scinode_app/static/controls.js
scinode_app/static/init_editor.js
scinode_app/static/json_components.js
scinode_app/static/logo.png
scinode_app/static/nodetree_editor.js
scinode_app/static/nodetree_node_table.js
scinode_app/static/scinode_components.js
scinode_app/static/scinode_editor.js
scinode_app-0.2.0.dist-info/LICENSE
scinode_app-0.2.0.dist-info/METADATA
scinode_app-0.2.0.dist-info/WHEEL
scinode_app-0.2.0.dist-info/top_level.txt
scinode_app-0.2.0.dist-info/RECORD
