Metadata-Version: 2.1
Name: scinode-app
Version: 0.2.0
Summary: Design computational workflow using nodes.
Home-page: https://github.com/scinode/scinode-app
Author: Xing Wang
Author-email: xingwang1991@gmail.com
License: MIT License
Requires-Python: >=3.6
License-File: LICENSE
Requires-Dist: flask
Requires-Dist: scinode
Requires-Dist: numpy
Requires-Dist: click
